[
    {
        "categoryId": "CodeValue",
        "name": "CodeResource",
        "itemsInStock": 10
    },
    {
        "categoryId": "CodeValue",
        "itemsInStock": 1,
        "name": "CodeStat"
    },
    {
        "categoryId": "Microsoft",
        "itemsInStock": 100,
        "name": "Microsoft"
    },
    {
        "categoryId": "Apple",    
        "itemsInStock": 20,
        "name": "Macbook Pro"
    },
    {
        "categoryId": "Apple",    
        "itemsInStock": 14,
        "name": "Ipad"
    },
    {
        "categoryId": "Apple",    
        "itemsInStock": 40,
        "name": "Macbook Pro 2010"
    },
    {
        "categoryId": "Apple",    
        "itemsInStock": 70,
        "name": "Iphone X"
    },
    {
        "categoryId": "Apple",    
        "itemsInStock": 643,
        "name": "Iphone 7"
    },
    {
        "categoryId": "Apple",    
        "itemsInStock": 10,
        "name": "Pavilion"
    },
    {
        "categoryId": "Microsoft",
        "itemsInStock": 40,
        "name": "Lenovo"
    },
    {
        "categoryId": "Microsoft",
        "itemsInStock": 87,
        "name": "Mouse Microsoft"
    },
    {
        "categoryId": "Apple",    
        "itemsInStock": 634,
        "name": "AirPods"
    }
]